circuit.v
`timescale 1ns / 1ps
`include "iob_lib.vh"

module circuit
  (
   `INPUT(rst,1),
   `INPUT(clk,1),
   `INPUT(en,1),
   `INPUT(x,32),
   `OUTPUT(y,32)
   );

   `SIGNAL(cnt, 32)
   `SIGNAL(max, 32)
   `SIGNAL(s_out, 32)

   `REG_ARE(clk, rst, 1'b0, cnt!=99, s_out, max)
   `SIGNAL2OUT(y, s_out)

   //iteration counter
   `COUNTER_ARE(clk, rst, cnt!=99, cnt)

   `COMB begin
   if (x > max) begin
    max = x;
    end else
    max = s_out;
   end

endmodule

circuit_tb.v
`timescale 1ns / 1ps
`include "iob_lib.vh"

module circuit_tb;

   `CLOCK(clk, 10)
   `RESET(rst, 1, 10)
   `SIGNAL(en, 1)
   `SIGNAL(x, 32)
   `SIGNAL_OUT(y, 32)

   integer i;

   initial begin
      $dumpfile("circuit.vcd");
      $dumpvars();
      en=1;
      for (i=0; i<100; i=i+1) begin
         @(posedge clk) #1 x = $random;
         @(posedge clk) #1 $write("Max Number: %d\n", y);
      end

      @(posedge clk) #200 $finish;

   end

   circuit c0
     (
      .rst(rst),
      .clk(clk),
      .en(en),
      .x(x),
      .y(y)
      );


endmodule

circuit.vcd
$date
	Tue Nov 17 22:28:47 2020
$end
$version
	Icarus Verilog
$end
$timescale
	1ps
$end
$scope module circuit_tb $end
$var wire 32 ! y [31:0] $end
$var reg 1 " clk $end
$var reg 1 # en $end
$var reg 1 $ rst $end
$var reg 32 % x [31:0] $end
$var integer 32 & i [31:0] $end
$scope module c0 $end
$var wire 1 " clk $end
$var wire 1 # en $end
$var wire 1 $ rst $end
$var wire 32 ' x [31:0] $end
$var wire 32 ( y [31:0] $end
$var reg 32 ) cnt [31:0] $end
$var reg 32 * max [31:0] $end
$var reg 32 + s_out [31:0] $end
$upscope $end
$upscope $end
$enddefinitions $end
#0
$dumpvars
bx +
bx *
bx )
bx (
bx '
b0 &
bx %
0$
1#
1"
bx !
$end
#1000
b0 *
b0 )
b0 !
b0 (
b0 +
1$
#5000
0"
#10000
1"
#11000
b10010000101010011010100100100 *
b10010000101010011010100100100 %
b10010000101010011010100100100 '
0$
#15000
0"
#20000
b1 )
b10010000101010011010100100100 !
b10010000101010011010100100100 (
b10010000101010011010100100100 +
1"
#21000
b1 &
#25000
0"
#30000
b10 )
1"
#31000
b11000000100010010101111010000001 *
b11000000100010010101111010000001 %
b11000000100010010101111010000001 '
#35000
0"
#40000
b11 )
b11000000100010010101111010000001 !
b11000000100010010101111010000001 (
b11000000100010010101111010000001 +
1"
#41000
b10 &
#45000
0"
#50000
b100 )
1"
#51000
b10000100100001001101011000001001 %
b10000100100001001101011000001001 '
#55000
0"
#60000
b101 )
1"
#61000
b11 &
#65000
0"
#70000
b110 )
1"
#71000
b10110001111100000101011001100011 %
b10110001111100000101011001100011 '
#75000
0"
#80000
b111 )
1"
#81000
b100 &
#85000
0"
#90000
b1000 )
1"
#91000
b110101110010111101100001101 %
b110101110010111101100001101 '
#95000
0"
#100000
b1001 )
1"
#101000
b101 &
#105000
0"
#110000
b1010 )
1"
#111000
b1000110110111111001100110001101 %
b1000110110111111001100110001101 '
#115000
0"
#120000
b1011 )
1"
#121000
b110 &
#125000
0"
#130000
b1100 )
1"
#131000
b10110010110000101000010001100101 %
b10110010110000101000010001100101 '
#135000
0"
#140000
b1101 )
1"
#141000
b111 &
#145000
0"
#150000
b1110 )
1"
#151000
b10001001001101110101001000010010 %
b10001001001101110101001000010010 '
#155000
0"
#160000
b1111 )
1"
#161000
b1000 &
#165000
0"
#170000
b10000 )
1"
#171000
b111100111110001100000001 %
b111100111110001100000001 '
#175000
0"
#180000
b10001 )
1"
#181000
b1001 &
#185000
0"
#190000
b10010 )
1"
#191000
b110110101111100110100001101 %
b110110101111100110100001101 '
#195000
0"
#200000
b10011 )
1"
#201000
b1010 &
#205000
0"
#210000
b10100 )
1"
#211000
b111011001000111111000101110110 %
b111011001000111111000101110110 '
#215000
0"
#220000
b10101 )
1"
#221000
b1011 &
#225000
0"
#230000
b10110 )
1"
#231000
b11110100011011100110100111101 %
b11110100011011100110100111101 '
#235000
0"
#240000
b10111 )
1"
#241000
b1100 &
#245000
0"
#250000
b11000 )
1"
#251000
b1110110110101000101011111101101 %
b1110110110101000101011111101101 '
#255000
0"
#260000
b11001 )
1"
#261000
b1101 &
#265000
0"
#270000
b11010 )
1"
#271000
b1000110001011011111011110001100 %
b1000110001011011111011110001100 '
#275000
0"
#280000
b11011 )
1"
#281000
b1110 &
#285000
0"
#290000
b11100 )
1"
#291000
b1111100111111011110100111111001 %
b1111100111111011110100111111001 '
#295000
0"
#300000
b11101 )
1"
#301000
b1111 &
#305000
0"
#310000
b11110 )
1"
#311000
b11100011001101110010010011000110 *
b11100011001101110010010011000110 %
b11100011001101110010010011000110 '
#315000
0"
#320000
b11111 )
b11100011001101110010010011000110 !
b11100011001101110010010011000110 (
b11100011001101110010010011000110 +
1"
#321000
b10000 &
#325000
0"
#330000
b100000 )
1"
#331000
b11100010111101111000010011000101 %
b11100010111101111000010011000101 '
#335000
0"
#340000
b100001 )
1"
#341000
b10001 &
#345000
0"
#350000
b100010 )
1"
#351000
b11010101000100111101001010101010 %
b11010101000100111101001010101010 '
#355000
0"
#360000
b100011 )
1"
#361000
b10010 &
#365000
0"
#370000
b100100 )
1"
#371000
b1110010101011111111011111100101 %
b1110010101011111111011111100101 '
#375000
0"
#380000
b100101 )
1"
#381000
b10011 &
#385000
0"
#390000
b100110 )
1"
#391000
b10111011110100100111001001110111 %
b10111011110100100111001001110111 '
#395000
0"
#400000
b100111 )
1"
#401000
b10100 &
#405000
0"
#410000
b101000 )
1"
#411000
b10001001001100101101011000010010 %
b10001001001100101101011000010010 '
#415000
0"
#420000
b101001 )
1"
#421000
b10101 &
#425000
0"
#430000
b101010 )
1"
#431000
b1000111111011001101101110001111 %
b1000111111011001101101110001111 '
#435000
0"
#440000
b101011 )
1"
#441000
b10110 &
#445000
0"
#450000
b101100 )
1"
#451000
b1111001001100000110100111110010 %
b1111001001100000110100111110010 '
#455000
0"
#460000
b101101 )
1"
#461000
b10111 &
#465000
0"
#470000
b101110 )
1"
#471000
b11100111011101101001011011001110 *
b11100111011101101001011011001110 %
b11100111011101101001011011001110 '
#475000
0"
#480000
b101111 )
b11100111011101101001011011001110 !
b11100111011101101001011011001110 (
b11100111011101101001011011001110 +
1"
#481000
b11000 &
#485000
0"
#490000
b110000 )
1"
#491000
b11110100000000000111101011101000 *
b11110100000000000111101011101000 %
b11110100000000000111101011101000 '
#495000
0"
#500000
b110001 )
b11110100000000000111101011101000 !
b11110100000000000111101011101000 (
b11110100000000000111101011101000 +
1"
#501000
b11001 &
#505000
0"
#510000
b110010 )
1"
#511000
b11100010110010100100111011000101 %
b11100010110010100100111011000101 '
#515000
0"
#520000
b110011 )
1"
#521000
b11010 &
#525000
0"
#530000
b110100 )
1"
#531000
b101110010110000100100101011100 %
b101110010110000100100101011100 '
#535000
0"
#540000
b110101 )
1"
#541000
b11011 &
#545000
0"
#550000
b110110 )
1"
#551000
b11011110100011100010100010111101 %
b11011110100011100010100010111101 '
#555000
0"
#560000
b110111 )
1"
#561000
b11100 &
#565000
0"
#570000
b111000 )
1"
#571000
b10010110101010110101100000101101 %
b10010110101010110101100000101101 '
#575000
0"
#580000
b111001 )
1"
#581000
b11101 &
#585000
0"
#590000
b111010 )
1"
#591000
b10110010101001110010011001100101 %
b10110010101001110010011001100101 '
#595000
0"
#600000
b111011 )
1"
#601000
b11110 &
#605000
0"
#610000
b111100 )
1"
#611000
b10110001111011110110001001100011 %
b10110001111011110110001001100011 '
#615000
0"
#620000
b111101 )
1"
#621000
b11111 &
#625000
0"
#630000
b111110 )
1"
#631000
b101011100111000011100001010 %
b101011100111000011100001010 '
#635000
0"
#640000
b111111 )
1"
#641000
b100000 &
#645000
0"
#650000
b1000000 )
1"
#651000
b11000000001110110010001010000000 %
b11000000001110110010001010000000 '
#655000
0"
#660000
b1000001 )
1"
#661000
b100001 &
#665000
0"
#670000
b1000010 )
1"
#671000
b10000011001000010000100100000 %
b10000011001000010000100100000 '
#675000
0"
#680000
b1000011 )
1"
#681000
b100010 &
#685000
0"
#690000
b1000100 )
1"
#691000
b1010101011110000100010110101010 %
b1010101011110000100010110101010 '
#695000
0"
#700000
b1000101 )
1"
#701000
b100011 &
#705000
0"
#710000
b1000110 )
1"
#711000
b11001110110011001100110010011101 %
b11001110110011001100110010011101 '
#715000
0"
#720000
b1000111 )
1"
#721000
b100100 &
#725000
0"
#730000
b1001000 )
1"
#731000
b11001011001000000011111010010110 %
b11001011001000000011111010010110 '
#735000
0"
#740000
b1001001 )
1"
#741000
b100101 &
#745000
0"
#750000
b1001010 )
1"
#751000
b10001001100000111011100000010011 %
b10001001100000111011100000010011 '
#755000
0"
#760000
b1001011 )
1"
#761000
b100110 &
#765000
0"
#770000
b1001100 )
1"
#771000
b10000110101111000011100000001101 %
b10000110101111000011100000001101 '
#775000
0"
#780000
b1001101 )
1"
#781000
b100111 &
#785000
0"
#790000
b1001110 )
1"
#791000
b10101001101001111101011001010011 %
b10101001101001111101011001010011 '
#795000
0"
#800000
b1001111 )
1"
#801000
b101000 &
#805000
0"
#810000
b1010000 )
1"
#811000
b110101100111111101110101101011 %
b110101100111111101110101101011 '
#815000
0"
#820000
b1010001 )
1"
#821000
b101001 &
#825000
0"
#830000
b1010010 )
1"
#831000
b11101010101001100010101011010101 %
b11101010101001100010101011010101 '
#835000
0"
#840000
b1010011 )
1"
#841000
b101010 &
#845000
0"
#850000
b1010100 )
1"
#851000
b10000001000101110100101000000010 %
b10000001000101110100101000000010 '
#855000
0"
#860000
b1010101 )
1"
#861000
b101011 &
#865000
0"
#870000
b1010110 )
1"
#871000
b11010111010101100011111010101110 %
b11010111010101100011111010101110 '
#875000
0"
#880000
b1010111 )
1"
#881000
b101100 &
#885000
0"
#890000
b1011000 )
1"
#891000
b1110111111111110100100011101 %
b1110111111111110100100011101 '
#895000
0"
#900000
b1011001 )
1"
#901000
b101101 &
#905000
0"
#910000
b1011010 )
1"
#911000
b11100111110001010111001011001111 %
b11100111110001010111001011001111 '
#915000
0"
#920000
b1011011 )
1"
#921000
b101110 &
#925000
0"
#930000
b1011100 )
1"
#931000
b10001100001000100100100100011 %
b10001100001000100100100100011 '
#935000
0"
#940000
b1011101 )
1"
#941000
b101111 &
#945000
0"
#950000
b1011110 )
1"
#951000
b101000010010110010100001010 %
b101000010010110010100001010 '
#955000
0"
#960000
b1011111 )
1"
#961000
b110000 &
#965000
0"
#970000
b1100000 )
1"
#971000
b11100101011100110000101011001010 %
b11100101011100110000101011001010 '
#975000
0"
#980000
b1100001 )
1"
#981000
b110001 &
#985000
0"
#990000
b1100010 )
1"
#991000
b10011110001100010100110000111100 %
b10011110001100010100110000111100 '
#995000
0"
#1000000
b1100011 )
1"
#1001000
b110010 &
#1005000
0"
#1010000
1"
#1011000
b1111001011010001011110111110010 %
b1111001011010001011110111110010 '
#1015000
0"
#1020000
1"
#1021000
b110011 &
#1025000
0"
#1030000
1"
#1031000
b1000101001011100110000110001010 %
b1000101001011100110000110001010 '
#1035000
0"
#1040000
1"
#1041000
b110100 &
#1045000
0"
#1050000
1"
#1051000
b100000110001001011001101000001 %
b100000110001001011001101000001 '
#1055000
0"
#1060000
1"
#1061000
b110101 &
#1065000
0"
#1070000
1"
#1071000
b11101100010010110011010011011000 %
b11101100010010110011010011011000 '
#1075000
0"
#1080000
1"
#1081000
b110110 &
#1085000
0"
#1090000
1"
#1091000
b111100001000001111001101111000 %
b111100001000001111001101111000 '
#1095000
0"
#1100000
1"
#1101000
b110111 &
#1105000
0"
#1110000
1"
#1111000
b11000100100010100001001010001001 %
b11000100100010100001001010001001 '
#1115000
0"
#1120000
1"
#1121000
b111000 &
#1125000
0"
#1130000
1"
#1131000
b1110101110001010000110111101011 %
b1110101110001010000110111101011 '
#1135000
0"
#1140000
1"
#1141000
b111001 &
#1145000
0"
#1150000
1"
#1151000
b1011011000000100110010110110110 %
b1011011000000100110010110110110 '
#1155000
0"
#1160000
1"
#1161000
b111010 &
#1165000
0"
#1170000
1"
#1171000
b1100011010010111111100111000110 %
b1100011010010111111100111000110 '
#1175000
0"
#1180000
1"
#1181000
b111011 &
#1185000
0"
#1190000
1"
#1191000
b1010111000101010001001110101110 %
b1010111000101010001001110101110 '
#1195000
0"
#1200000
1"
#1201000
b111100 &
#1205000
0"
#1210000
1"
#1211000
b11011110011101010000001010111100 %
b11011110011101010000001010111100 '
#1215000
0"
#1220000
1"
#1221000
b111101 &
#1225000
0"
#1230000
1"
#1231000
b10101000011111101110100101010 %
b10101000011111101110100101010 '
#1235000
0"
#1240000
1"
#1241000
b111110 &
#1245000
0"
#1250000
1"
#1251000
b10000101110101111001101000001011 %
b10000101110101111001101000001011 '
#1255000
0"
#1260000
1"
#1261000
b111111 &
#1265000
0"
#1270000
1"
#1271000
b10111000100101111011111001110001 %
b10111000100101111011111001110001 '
#1275000
0"
#1280000
1"
#1281000
b1000000 &
#1285000
0"
#1290000
1"
#1291000
b1000010111100100100000110000101 %
b1000010111100100100000110000101 '
#1295000
0"
#1300000
1"
#1301000
b1000001 &
#1305000
0"
#1310000
1"
#1311000
b100111111100100101010101001111 %
b100111111100100101010101001111 '
#1315000
0"
#1320000
1"
#1321000
b1000010 &
#1325000
0"
#1330000
1"
#1331000
b10011101110011000110000000111011 %
b10011101110011000110000000111011 '
#1335000
0"
#1340000
1"
#1341000
b1000011 &
#1345000
0"
#1350000
1"
#1351000
b11101000001100011001100111010 %
b11101000001100011001100111010 '
#1355000
0"
#1360000
1"
#1361000
b1000100 &
#1365000
0"
#1370000
1"
#1371000
b10111111001000110011001001111110 %
b10111111001000110011001001111110 '
#1375000
0"
#1380000
1"
#1381000
b1000101 &
#1385000
0"
#1390000
1"
#1391000
b1010101010100100101100010101 %
b1010101010100100101100010101 '
#1395000
0"
#1400000
1"
#1401000
b1000110 &
#1405000
0"
#1410000
1"
#1411000
b1111000110110011001101111110001 %
b1111000110110011001101111110001 '
#1415000
0"
#1420000
1"
#1421000
b1000111 &
#1425000
0"
#1430000
1"
#1431000
b1101100100111000100101111011001 %
b1101100100111000100101111011001 '
#1435000
0"
#1440000
1"
#1441000
b1001000 &
#1445000
0"
#1450000
1"
#1451000
b110001001000110000011101100010 %
b110001001000110000011101100010 '
#1455000
0"
#1460000
1"
#1461000
b1001001 &
#1465000
0"
#1470000
1"
#1471000
b100110001101011111101101001100 %
b100110001101011111101101001100 '
#1475000
0"
#1480000
1"
#1481000
b1001010 &
#1485000
0"
#1490000
1"
#1491000
b1001111101000010101010110011111 %
b1001111101000010101010110011111 '
#1495000
0"
#1500000
1"
#1501000
b1001011 &
#1505000
0"
#1510000
1"
#1511000
b1000111101110011010000110001111 %
b1000111101110011010000110001111 '
#1515000
0"
#1520000
1"
#1521000
b1001100 &
#1525000
0"
#1530000
1"
#1531000
b1111100011011011010100111111000 %
b1111100011011011010100111111000 '
#1535000
0"
#1540000
1"
#1541000
b1001101 &
#1545000
0"
#1550000
1"
#1551000
b11011011110011010110000010110111 %
b11011011110011010110000010110111 '
#1555000
0"
#1560000
1"
#1561000
b1001110 &
#1565000
0"
#1570000
1"
#1571000
b11001111110001000101011010011111 %
b11001111110001000101011010011111 '
#1575000
0"
#1580000
1"
#1581000
b1001111 &
#1585000
0"
#1590000
1"
#1591000
b10101110011111011001010001011100 %
b10101110011111011001010001011100 '
#1595000
0"
#1600000
1"
#1601000
b1010000 &
#1605000
0"
#1610000
1"
#1611000
b10101101110010111100000001011011 %
b10101101110010111100000001011011 '
#1615000
0"
#1620000
1"
#1621000
b1010001 &
#1625000
0"
#1630000
1"
#1631000
b1000100110111100011011110001001 %
b1000100110111100011011110001001 '
#1635000
0"
#1640000
1"
#1641000
b1010010 &
#1645000
0"
#1650000
1"
#1651000
b10100100101011100011001001001001 %
b10100100101011100011001001001001 '
#1655000
0"
#1660000
1"
#1661000
b1010011 &
#1665000
0"
#1670000
1"
#1671000
b11101000001000110011111011010000 %
b11101000001000110011111011010000 '
#1675000
0"
#1680000
1"
#1681000
b1010100 &
#1685000
0"
#1690000
1"
#1691000
b11101011111111101100000011010111 %
b11101011111111101100000011010111 '
#1695000
0"
#1700000
1"
#1701000
b1010101 &
#1705000
0"
#1710000
1"
#1711000
b10101000110001111111110001010001 %
b10101000110001111111110001010001 '
#1715000
0"
#1720000
1"
#1721000
b1010110 &
#1725000
0"
#1730000
1"
#1731000
b1001011001000010010111110010110 %
b1001011001000010010111110010110 '
#1735000
0"
#1740000
1"
#1741000
b1010111 &
#1745000
0"
#1750000
1"
#1751000
b110000111010111111100001100 %
b110000111010111111100001100 '
#1755000
0"
#1760000
1"
#1761000
b1011000 &
#1765000
0"
#1770000
1"
#1771000
b11100001001011001100111011000010 %
b11100001001011001100111011000010 '
#1775000
0"
#1780000
1"
#1781000
b1011001 &
#1785000
0"
#1790000
1"
#1791000
b1100100010101111110110111001000 %
b1100100010101111110110111001000 '
#1795000
0"
#1800000
1"
#1801000
b1011010 &
#1805000
0"
#1810000
1"
#1811000
b10111011100000100101101001110111 %
b10111011100000100101101001110111 '
#1815000
0"
#1820000
1"
#1821000
b1011011 &
#1825000
0"
#1830000
1"
#1831000
b11110111100101110110100111101 %
b11110111100101110110100111101 '
#1835000
0"
#1840000
1"
#1841000
b1011100 &
#1845000
0"
#1850000
1"
#1851000
b1001000011001101101100010010 %
b1001000011001101101100010010 '
#1855000
0"
#1860000
1"
#1861000
b1011101 &
#1865000
0"
#1870000
1"
#1871000
b10111111000001010000000001111110 %
b10111111000001010000000001111110 '
#1875000
0"
#1880000
1"
#1881000
b1011110 &
#1885000
0"
#1890000
1"
#1891000
b110110111001011000000101101101 %
b110110111001011000000101101101 '
#1895000
0"
#1900000
1"
#1901000
b1011111 &
#1905000
0"
#1910000
1"
#1911000
b11100110110011110011100111001 %
b11100110110011110011100111001 '
#1915000
0"
#1920000
1"
#1921000
b1100000 &
#1925000
0"
#1930000
1"
#1931000
b1111110100101000111100011111 %
b1111110100101000111100011111 '
#1935000
0"
#1940000
1"
#1941000
b1100001 &
#1945000
0"
#1950000
1"
#1951000
b11101001111010111111011011010011 %
b11101001111010111111011011010011 '
#1955000
0"
#1960000
1"
#1961000
b1100010 &
#1965000
0"
#1970000
1"
#1971000
b1000010110110010010111110000101 %
b1000010110110010010111110000101 '
#1975000
0"
#1980000
1"
#1981000
b1100011 &
#1985000
0"
#1990000
1"
#1991000
b10111100000101001000100001111000 %
b10111100000101001000100001111000 '
#1995000
0"
#2000000
1"
#2001000
b1100100 &
